ncscli/WorldCountryBoundaries.csv
ncscli/__init__.py
ncscli/batchRunner.py
ncscli/jsonToInv.py
ncscli/jsonToKnownHosts.py
ncscli/ncs.py
ncscli/plotInstanceMap.py
ncscli/purgeKnownHosts.py
ncscli/tellInstances.py
ncscli-1.2.3.data/scripts/jsonToInv.py
ncscli-1.2.3.data/scripts/ncs.py
ncscli-1.2.3.data/scripts/purgeKnownHosts.py
ncscli-1.2.3.data/scripts/tellInstances.py
ncsexamples/batchMode/LoadTestHeader_005.jpg
ncsexamples/batchMode/Puppeteer.js
ncsexamples/batchMode/SpinningCube.blend
ncsexamples/batchMode/TestPlan.jmx
ncsexamples/batchMode/TestPlan_RampLong.jmx
ncsexamples/batchMode/TestPlan_RampLong_LessSlow.jmx
ncsexamples/batchMode/TestPlan_RampLong_MoreSlow.jmx
ncsexamples/batchMode/TestPlan_dynatrace.jmx
ncsexamples/batchMode/TestPlan_dynatrace_RampLong.jmx
ncsexamples/batchMode/WorldCountryBoundaries.csv
ncsexamples/batchMode/dlUrlList.txt
ncsexamples/batchMode/helloFrame.c
ncsexamples/batchMode/helloFrame.java
ncsexamples/batchMode/helloFrame.js
ncsexamples/batchMode/helloFrameCpp.cpp
ncsexamples/batchMode/helloFrameGo.go
ncsexamples/batchMode/helloLocation.py
ncsexamples/batchMode/installJMeter5.4.1.sh
ncsexamples/batchMode/installJdk11.sh
ncsexamples/batchMode/jmxTool.py
ncsexamples/batchMode/mergeBatchOutput.py
ncsexamples/batchMode/perfmonClient.py
ncsexamples/batchMode/plotFrame.py
ncsexamples/batchMode/plotGatlingOutput.py
ncsexamples/batchMode/plotJMeterHist.py
ncsexamples/batchMode/plotJMeterMulti.py
ncsexamples/batchMode/plotJMeterOutput.py
ncsexamples/batchMode/plotJMeterRegression.py
ncsexamples/batchMode/plotK6Output.py
ncsexamples/batchMode/plotLocustOutput.py
ncsexamples/batchMode/plotTaurusOutput.py
ncsexamples/batchMode/processPuppeteerOutput.py
ncsexamples/batchMode/pytestQuick.sh
ncsexamples/batchMode/reportGatlingOutput.py
ncsexamples/batchMode/runBatchBinary.py
ncsexamples/batchMode/runBatchBinaryCpp.py
ncsexamples/batchMode/runBatchBinaryGo.py
ncsexamples/batchMode/runBatchBlender.py
ncsexamples/batchMode/runBatchDownload.py
ncscli-1.2.3.dist-info/LICENSE
ncscli-1.2.3.dist-info/METADATA
ncscli-1.2.3.dist-info/WHEEL
ncscli-1.2.3.dist-info/top_level.txt
ncscli-1.2.3.dist-info/RECORD
