Metadata-Version: 2.1
Name: ncscli
Version: 1.2.3
Summary: ncscli is the command-line and python interface for Neocortix Cloud Services.
Home-page: https://github.com/neocortix/ncscli
Author: Neocortix, Inc.
Author-email: info@neocortix.com
License: UNKNOWN
Platform: UNKNOWN
Classifier: Programming Language :: Python :: 3
Classifier: License :: OSI Approved :: MIT License
Classifier: Operating System :: OS Independent
Requires-Python: >=3.6
Requires-Dist: python-dateutil (>=2.8.0)
Requires-Dist: requests (>=2.12.4)
Requires-Dist: asyncssh (>=1.16.1)
Requires-Dist: psutil (>=5.7.2)
